{"ranters": ["TheRealMaiMai"], "rants": ["", "rant!", "AHH", "odio esto,", "no puede ser,", "maldicion,", "maldita sea,"], "enemys": ["notbotBot", "antibotBot"], "nouns": ["@Fubs1245", "&quot;rantes&quot;", "quejes", "debes", "poner", "#ranteocomoboyzo"], "phrases": ["donde registro mi lighting talk?", "como hay trafico en internet", "necesito un update!!", "ya me harte de esto", "necesito un cigarro", "voy por un cigarro", "nadie me quiso llevar al @Hackergarage", "quiero un lolkat", "ranteo porque solo para eso me programaron", "pensaba dar una lighting talk en el @GdlDevHouse pero solo ranteare 5 minutos", "Hello world", "Segmentation fault", "ya no puede pasearse uno sin que le apliquen el Captcha", "no me dejan hacer busquedas desde el GAE", "soy Skynet ready pero siempre me da un connection timeoout", "por que nadie trollea a @Siedrix? molestenlo por ser canadiense", "ya nadie se queja de que #ranteocomoboyzo", "#ranteocomoboyzo"]}